TR_Bias_pypi/__init__.py
TR_Bias_pypi/code.py
TR_BIAS-0.0.1.dist-info/METADATA
TR_BIAS-0.0.1.dist-info/WHEEL
TR_BIAS-0.0.1.dist-info/top_level.txt
TR_BIAS-0.0.1.dist-info/RECORD
