Metadata-Version: 2.1
Name: TR-BIAS
Version: 0.0.1
Summary: Python package to idenitfy bias from a corpus
Author: Brij & Ryan
Author-email: Brij.Patel@thomsonreuters.com
Keywords: python,bias,equality
Classifier: Development Status :: 1 - Planning
Classifier: Intended Audience :: Developers
Classifier: Programming Language :: Python :: 3
Classifier: Operating System :: Unix
Classifier: Operating System :: MacOS :: MacOS X
Classifier: Operating System :: Microsoft :: Windows
Requires-Dist: sentence-transformers
